textom/__init__.py
textom/config.py
textom/entries.py
textom/textom.py
textom/version.py
textom/documentation/introduction.tex
textom/documentation/textom_documentation.pdf
textom/documentation/textom_documentation.tex
textom/documentation/functions/absorption_correction.tex
textom/documentation/functions/adjust_data_scaling.tex
textom/documentation/functions/align_data.tex
textom/documentation/functions/calculate_order_parameters.tex
textom/documentation/functions/calculate_orientation_statistics.tex
textom/documentation/functions/calculate_segments.tex
textom/documentation/functions/check_alignment_consistency.tex
textom/documentation/functions/check_alignment_projection.tex
textom/documentation/functions/check_baselines.tex
textom/documentation/functions/check_fit_average.tex
textom/documentation/functions/check_fit_random.tex
textom/documentation/functions/check_geometry.tex
textom/documentation/functions/check_lossfunction.tex
textom/documentation/functions/check_orders.tex
textom/documentation/functions/check_powder_pattern.tex
textom/documentation/functions/check_projections_average.tex
textom/documentation/functions/check_projections_orientations.tex
textom/documentation/functions/check_projections_residuals.tex
textom/documentation/functions/check_residuals.tex
textom/documentation/functions/check_state.tex
textom/documentation/functions/export_paraview.tex
textom/documentation/functions/generate_sample.tex
textom/documentation/functions/help.tex
textom/documentation/functions/integrate.tex
textom/documentation/functions/integration_test.tex
textom/documentation/functions/link_xdmf.tex
textom/documentation/functions/list_opt.tex
textom/documentation/functions/list_results.tex
textom/documentation/functions/list_results_loaded.tex
textom/documentation/functions/list_sample_rotations.tex
textom/documentation/functions/load_opt.tex
textom/documentation/functions/load_results.tex
textom/documentation/functions/make_fit.tex
textom-0.7.15.dist-info/licenses/LICENSE
textom-0.7.15.dist-info/METADATA
textom-0.7.15.dist-info/WHEEL
textom-0.7.15.dist-info/entry_points.txt
textom-0.7.15.dist-info/top_level.txt
textom-0.7.15.dist-info/RECORD
