Metadata-Version: 2.4
Name: TexTOM
Version: 0.7.15
Summary: A program for texture simulations.
Home-page: https://gitlab.fresnel.fr/textom/textom.git
Author: Moritz Frewein, Marc Allain, Tilman Gruenewald
Author-email: textom@fresnel.fr
Classifier: Programming Language :: Python :: 3
Classifier: License :: OSI Approved :: MIT License
Classifier: Operating System :: OS Independent
Requires-Python: >=3.9, <=3.13
License-File: LICENSE
Requires-Dist: mumott<=2.2,>=2.0
Requires-Dist: pyfai<=2025.1,>=2023
Requires-Dist: orix<=0.13.3,>=0.13.0
Requires-Dist: psutil==7.0
Requires-Dist: scipy==1.15
Requires-Dist: threadpoolctl==3.6
Requires-Dist: ipython
Dynamic: author
Dynamic: author-email
Dynamic: classifier
Dynamic: description
Dynamic: description-content-type
Dynamic: home-page
Dynamic: license-file
Dynamic: requires-dist
Dynamic: requires-python
Dynamic: summary
